copysc/__init__.py
copysc/copyscreen.py
copysc-0.3.4.dist-info/DESCRIPTION.rst
copysc-0.3.4.dist-info/METADATA
copysc-0.3.4.dist-info/RECORD
copysc-0.3.4.dist-info/WHEEL
copysc-0.3.4.dist-info/metadata.json
copysc-0.3.4.dist-info/top_level.txt
