Metadata-Version: 2.0
Name: copysc
Version: 0.3.4
Summary: Small utility that translates a shared screenshot url into a markdown-ready *.png url. Works with dropbox, screencloud, and others.
Home-page: https://github.com/rv816/copysc
Author: Ryan Vass
Author-email: rvsax16@gmail.com
License: UNKNOWN
Platform: UNKNOWN
Classifier: Development Status :: 2 - Pre-Alpha
Classifier: Programming Language :: Python
Classifier: Programming Language :: Python :: 2
Classifier: Programming Language :: Python :: 2.7
Classifier: Programming Language :: Python :: 3
Classifier: Programming Language :: Python :: 3.4
Classifier: Programming Language :: Python :: 3.5
Requires-Dist: bs4
Requires-Dist: pyperclip
Requires-Dist: requests
